sphinx_autofixture/__init__.py
sphinx_autofixture/py.typed
sphinx_autofixture-0.4.1.dist-info/LICENSE
sphinx_autofixture-0.4.1.dist-info/METADATA
sphinx_autofixture-0.4.1.dist-info/WHEEL
sphinx_autofixture-0.4.1.dist-info/entry_points.txt
sphinx_autofixture-0.4.1.dist-info/RECORD
